{
  "_class": "group",
  "booleanOperation": -1,
  "clippingMaskMode": 0,
  "do_objectID": "0A4300A2-5EF3-447C-800E-167682A0686E",
  "exportOptions": {
    "_class": "exportOptions",
    "exportFormats": [
    ],
    "includedLayerIds": [
    ],
    "layerOptions": 0,
    "shouldTrim": false
  },
  "frame": {
    "_class": "rect",
    "constrainProportions": false,
    "height": 346,
    "width": 366,
    "x": 0,
    "y": 427
  },
  "groupLayout": {
    "_class": "MSImmutableFreeformGroupLayout"
  },
  "hasClickThrough": false,
  "hasClippingMask": false,
  "isFixedToViewport": false,
  "isFlippedHorizontal": false,
  "isFlippedVertical": false,
  "isLocked": false,
  "isVisible": true,
  "layerListExpandedType": 0,
  "layers": [
    {
      "class": "text",
      "id": "AAD7EEE0-93F2-4C5A-8658-F53C8E27401B"
    },
    {
      "class": "text",
      "id": "08AD3DBF-1900-4F3A-9419-8EF24E6EBC36"
    },
    {
      "class": "rectangle",
      "id": "EE7DD28A-C3E0-4609-A736-47EDA687E94D"
    },
    {
      "class": "text",
      "id": "991AF01F-0318-4EA0-96EE-DD763D3DEF9E"
    },
    {
      "class": "rectangle",
      "id": "FCD3F74A-9C1C-4CC0-86BE-B024B6F4C3B4"
    },
    {
      "class": "text",
      "id": "FDE296B9-BBFB-4F2E-91DF-22488CD359F4"
    },
    {
      "class": "text",
      "id": "C1BEA531-9675-4E21-9C85-E239AA355666"
    }
  ],
  "name": "Side Menu",
  "nameIsFixed": true,
  "resizingConstraint": 63,
  "resizingType": 0,
  "rotation": 0,
  "shouldBreakMaskChain": false,
  "style": {
    "_class": "style",
    "blur": {
      "_class": "blur",
      "center": "{0.5, 0.5}",
      "isEnabled": false,
      "motionAngle": 0,
      "radius": 10,
      "saturation": 1,
      "type": 0
    },
    "borderOptions": {
      "_class": "borderOptions",
      "dashPattern": [
      ],
      "isEnabled": true,
      "lineCapStyle": 0,
      "lineJoinStyle": 0
    },
    "borders": [
    ],
    "colorControls": {
      "_class": "colorControls",
      "brightness": 0,
      "contrast": 1,
      "hue": 0,
      "isEnabled": false,
      "saturation": 1
    },
    "contextSettings": {
      "_class": "graphicsContextSettings",
      "blendMode": 0,
      "opacity": 1
    },
    "do_objectID": "782B6C8E-68C3-4211-8CC1-388DF3500BB8",
    "endMarkerType": 0,
    "fills": [
    ],
    "innerShadows": [
    ],
    "miterLimit": 10,
    "shadows": [
    ],
    "startMarkerType": 0,
    "windingRule": 1
  }
}