{
  "_class": "shapePath",
  "booleanOperation": -1,
  "clippingMaskMode": 0,
  "do_objectID": "9ABF9579-6BDB-45E0-A6D7-F08CD7D96220",
  "edited": true,
  "exportOptions": {
    "_class": "exportOptions",
    "exportFormats": [
    ],
    "includedLayerIds": [
    ],
    "layerOptions": 0,
    "shouldTrim": false
  },
  "frame": {
    "_class": "rect",
    "constrainProportions": false,
    "height": 17.30795865570284,
    "width": 9.87956921598124,
    "x": 1045.200003213633,
    "y": 93.83371195404936
  },
  "hasClippingMask": false,
  "isClosed": false,
  "isFixedToViewport": false,
  "isFlippedHorizontal": false,
  "isFlippedVertical": false,
  "isLocked": false,
  "isVisible": true,
  "layerListExpandedType": 0,
  "name": "Fill-938",
  "nameIsFixed": false,
  "pointRadiusBehaviour": 1,
  "points": [
    {
      "_class": "curvePoint",
      "cornerRadius": 0,
      "curveFrom": "{1.0544951261149822, 0.73413930196580135}",
      "curveMode": 4,
      "curveTo": "{0.98264988828296929, 0.45893643796828659}",
      "hasCurveFrom": true,
      "hasCurveTo": false,
      "point": "{0.98264988828296929, 0.45893643796828659}"
    },
    {
      "_class": "curvePoint",
      "cornerRadius": 0,
      "curveFrom": "{0.36349973443766614, 1.0210092777248452}",
      "curveMode": 2,
      "curveTo": "{0.8966808767367821, 0.97559281148311461}",
      "hasCurveFrom": true,
      "hasCurveTo": true,
      "point": "{0.63000293335660573, 0.99827601796689247}"
    },
    {
      "_class": "curvePoint",
      "cornerRadius": 0,
      "curveFrom": "{-0.054500596317627797, 0.26585378168987661}",
      "curveMode": 2,
      "curveTo": "{0.089101454438304806, 0.81625953972888887}",
      "hasCurveFrom": true,
      "hasCurveTo": true,
      "point": "{0.01734464151438506, 0.54105665770498435}"
    },
    {
      "_class": "curvePoint",
      "cornerRadius": 0,
      "curveFrom": "{0.63649374268220138, -0.020966098733417413}",
      "curveMode": 2,
      "curveTo": "{0.10340102529119061, 0.024350236924778383}",
      "hasCurveFrom": true,
      "hasCurveTo": true,
      "point": "{0.36990317153264346, 0.0017171077503612938}"
    },
    {
      "_class": "curvePoint",
      "cornerRadius": 0,
      "curveFrom": "{0.98264988828296929, 0.45893643796828659}",
      "curveMode": 4,
      "curveTo": "{0.91089202268157476, 0.18373356195317891}",
      "hasCurveFrom": false,
      "hasCurveTo": true,
      "point": "{0.98264988828296929, 0.45893643796828659}"
    }
  ],
  "resizingConstraint": 63,
  "resizingType": 0,
  "rotation": 0,
  "shouldBreakMaskChain": false,
  "style": {
    "_class": "style",
    "blur": {
      "_class": "blur",
      "center": "{0.5, 0.5}",
      "isEnabled": false,
      "motionAngle": 0,
      "radius": 10.4,
      "saturation": 1,
      "type": 0
    },
    "borderOptions": {
      "_class": "borderOptions",
      "dashPattern": [
      ],
      "isEnabled": true,
      "lineCapStyle": 0,
      "lineJoinStyle": 0
    },
    "borders": [
    ],
    "colorControls": {
      "_class": "colorControls",
      "brightness": 0,
      "contrast": 1,
      "hue": 0,
      "isEnabled": false,
      "saturation": 1
    },
    "contextSettings": {
      "_class": "graphicsContextSettings",
      "blendMode": 0,
      "opacity": 1
    },
    "do_objectID": "0A602810-11A5-45E8-8602-B46293A7FD66",
    "endMarkerType": 0,
    "fills": [
      {
        "_class": "fill",
        "color": {
          "_class": "color",
          "alpha": 1,
          "blue": 1,
          "green": 1,
          "red": 1
        },
        "contextSettings": {
          "_class": "graphicsContextSettings",
          "blendMode": 0,
          "opacity": 1
        },
        "fillType": 0,
        "gradient": {
          "_class": "gradient",
          "elipseLength": 0,
          "from": "{0.5, 0}",
          "gradientType": 0,
          "stops": [
            {
              "_class": "gradientStop",
              "color": {
                "_class": "color",
                "alpha": 1,
                "blue": 1,
                "green": 1,
                "red": 1
              },
              "position": 0
            },
            {
              "_class": "gradientStop",
              "color": {
                "_class": "color",
                "alpha": 1,
                "blue": 0,
                "green": 0,
                "red": 0
              },
              "position": 1
            }
          ],
          "to": "{0.5, 1}"
        },
        "isEnabled": true,
        "noiseIndex": 0,
        "noiseIntensity": 0,
        "patternFillType": 1,
        "patternTileScale": 1
      }
    ],
    "innerShadows": [
    ],
    "miterLimit": 10,
    "shadows": [
    ],
    "startMarkerType": 0,
    "windingRule": 0
  }
}