{
  "_class": "shapePath",
  "booleanOperation": -1,
  "clippingMaskMode": 0,
  "do_objectID": "F94777A2-B0F2-49E7-8FD0-A5EFA0CC31F6",
  "edited": true,
  "exportOptions": {
    "_class": "exportOptions",
    "exportFormats": [
    ],
    "includedLayerIds": [
    ],
    "layerOptions": 0,
    "shouldTrim": false
  },
  "frame": {
    "_class": "rect",
    "constrainProportions": false,
    "height": 15.98867260313856,
    "width": 7.840775666791469,
    "x": 0.1040443332085335,
    "y": 0.8656230936855906
  },
  "hasClippingMask": false,
  "isClosed": false,
  "isFixedToViewport": false,
  "isFlippedHorizontal": false,
  "isFlippedVertical": false,
  "isLocked": false,
  "isVisible": true,
  "layerListExpandedType": 0,
  "name": "Stroke-1319",
  "nameIsFixed": false,
  "pointRadiusBehaviour": 1,
  "points": [
    {
      "_class": "curvePoint",
      "cornerRadius": 0,
      "curveFrom": "{0.13386120345679584, 0.083058609008838269}",
      "curveMode": 4,
      "curveTo": "{0.13386120345679584, 0.083058609008838269}",
      "hasCurveFrom": true,
      "hasCurveTo": false,
      "point": "{0.13386120345679584, 0.083058609008838269}"
    },
    {
      "_class": "curvePoint",
      "cornerRadius": 0,
      "curveFrom": "{0.24627355109391155, 0.97657452009176682}",
      "curveMode": 3,
      "curveTo": "{-0.13031334019873167, 0.51984283577630175}",
      "hasCurveFrom": true,
      "hasCurveTo": true,
      "point": "{0.083568560172771658, 0.77932237300727936}"
    },
    {
      "_class": "curvePoint",
      "cornerRadius": 0,
      "curveFrom": "{1, 0.99565469263467798}",
      "curveMode": 4,
      "curveTo": "{0.89344591674284157, 1.0146264594304066}",
      "hasCurveFrom": true,
      "hasCurveTo": true,
      "point": "{1, 0.99565469263467798}"
    },
    {
      "_class": "curvePoint",
      "cornerRadius": 0,
      "curveFrom": "{0.98131987581020341, -0.14758384360327642}",
      "curveMode": 4,
      "curveTo": "{0.87520792523829483, 0.65904138310055671}",
      "hasCurveFrom": true,
      "hasCurveTo": true,
      "point": "{0.97258774566012385, 0.15981294818763306}"
    },
    {
      "_class": "curvePoint",
      "cornerRadius": 0,
      "curveFrom": "{0.13386120345679584, 0.083058609008838269}",
      "curveMode": 4,
      "curveTo": "{0.13386120345679584, 0.083058609008838269}",
      "hasCurveFrom": false,
      "hasCurveTo": true,
      "point": "{0.13386120345679584, 0.083058609008838269}"
    }
  ],
  "resizingConstraint": 63,
  "resizingType": 0,
  "rotation": 0,
  "shouldBreakMaskChain": false,
  "style": {
    "_class": "style",
    "blur": {
      "_class": "blur",
      "center": "{0.5, 0.5}",
      "isEnabled": false,
      "motionAngle": 0,
      "radius": 10.4,
      "saturation": 1,
      "type": 0
    },
    "borderOptions": {
      "_class": "borderOptions",
      "dashPattern": [
      ],
      "isEnabled": true,
      "lineCapStyle": 1,
      "lineJoinStyle": 1
    },
    "borders": [
      {
        "_class": "border",
        "color": {
          "_class": "color",
          "alpha": 1,
          "blue": 0.7176470588235294,
          "green": 0.3137254901960784,
          "red": 0.1294117647058823
        },
        "contextSettings": {
          "_class": "graphicsContextSettings",
          "blendMode": 0,
          "opacity": 1
        },
        "fillType": 0,
        "gradient": {
          "_class": "gradient",
          "elipseLength": 0,
          "from": "{0.5, 0}",
          "gradientType": 0,
          "stops": [
            {
              "_class": "gradientStop",
              "color": {
                "_class": "color",
                "alpha": 1,
                "blue": 1,
                "green": 1,
                "red": 1
              },
              "position": 0
            },
            {
              "_class": "gradientStop",
              "color": {
                "_class": "color",
                "alpha": 1,
                "blue": 0,
                "green": 0,
                "red": 0
              },
              "position": 1
            }
          ],
          "to": "{0.5, 1}"
        },
        "isEnabled": true,
        "position": 0,
        "thickness": 1.3
      }
    ],
    "colorControls": {
      "_class": "colorControls",
      "brightness": 0,
      "contrast": 1,
      "hue": 0,
      "isEnabled": false,
      "saturation": 1
    },
    "contextSettings": {
      "_class": "graphicsContextSettings",
      "blendMode": 0,
      "opacity": 1
    },
    "do_objectID": "D5A61C2F-B628-494F-AD15-4A991BC1B7A0",
    "endMarkerType": 0,
    "fills": [
    ],
    "innerShadows": [
    ],
    "miterLimit": 10,
    "shadows": [
    ],
    "startMarkerType": 0,
    "windingRule": 1
  }
}