{
  "_class": "page",
  "booleanOperation": -1,
  "clippingMaskMode": 0,
  "do_objectID": "4DB8D7F4-3F69-46D7-9BC7-826B54EB1F3F",
  "exportOptions": {
    "_class": "exportOptions",
    "exportFormats": [
    ],
    "includedLayerIds": [
    ],
    "layerOptions": 0,
    "shouldTrim": false
  },
  "frame": {
    "_class": "rect",
    "constrainProportions": false,
    "height": 0,
    "width": 0,
    "x": 0,
    "y": 0
  },
  "groupLayout": {
    "_class": "MSImmutableFreeformGroupLayout"
  },
  "hasClickThrough": true,
  "hasClippingMask": false,
  "horizontalRulerData": {
    "_class": "rulerData",
    "base": -420,
    "guides": [
    ]
  },
  "includeInCloudUpload": true,
  "isFixedToViewport": false,
  "isFlippedHorizontal": false,
  "isFlippedVertical": false,
  "isLocked": false,
  "isVisible": true,
  "layerListExpandedType": 0,
  "layers": [
    {
      "class": "artboard",
      "id": "B469D282-3C2F-4153-8E33-AD554F653252"
    },
    {
      "class": "artboard",
      "id": "F71009FE-6AEB-4602-A1F8-DB9F462B89FD"
    },
    {
      "class": "artboard",
      "id": "68E846DB-D794-4251-89EC-99A334BD4CBE"
    },
    {
      "class": "artboard",
      "id": "D85DE9F1-E944-465C-8B0D-8BBC99E58ED8"
    },
    {
      "class": "artboard",
      "id": "FA5774C6-4D12-4168-91C0-41D2C90BD639"
    }
  ],
  "name": "Version 2: Draft for Approval",
  "nameIsFixed": true,
  "resizingConstraint": 63,
  "resizingType": 0,
  "rotation": 0,
  "shouldBreakMaskChain": false,
  "style": {
    "_class": "style",
    "blur": {
      "_class": "blur",
      "center": "{0.5, 0.5}",
      "isEnabled": false,
      "motionAngle": 0,
      "radius": 10,
      "saturation": 1,
      "type": 0
    },
    "borderOptions": {
      "_class": "borderOptions",
      "dashPattern": [
      ],
      "isEnabled": true,
      "lineCapStyle": 0,
      "lineJoinStyle": 0
    },
    "borders": [
    ],
    "colorControls": {
      "_class": "colorControls",
      "brightness": 0,
      "contrast": 1,
      "hue": 0,
      "isEnabled": false,
      "saturation": 1
    },
    "contextSettings": {
      "_class": "graphicsContextSettings",
      "blendMode": 0,
      "opacity": 1
    },
    "do_objectID": "4E413563-4DF1-44B6-80E1-726B9C0CD2F4",
    "endMarkerType": 0,
    "fills": [
    ],
    "innerShadows": [
    ],
    "miterLimit": 10,
    "shadows": [
    ],
    "startMarkerType": 0,
    "windingRule": 1
  },
  "verticalRulerData": {
    "_class": "rulerData",
    "base": -340,
    "guides": [
    ]
  }
}