{
  "_class": "artboard",
  "backgroundColor": {
    "_class": "color",
    "alpha": 1,
    "blue": 0.7814747702269565,
    "green": 0.8352864583333334,
    "red": 0.7656527263362234
  },
  "booleanOperation": -1,
  "clippingMaskMode": 0,
  "do_objectID": "6101CB45-294A-4416-A046-AE079F752AC4",
  "exportOptions": {
    "_class": "exportOptions",
    "exportFormats": [
      {
        "_class": "exportFormat",
        "absoluteSize": 0,
        "fileFormat": "png",
        "name": "",
        "namingScheme": 0,
        "scale": 3,
        "visibleScaleType": 0
      }
    ],
    "includedLayerIds": [
    ],
    "layerOptions": 0,
    "shouldTrim": false
  },
  "frame": {
    "_class": "rect",
    "constrainProportions": false,
    "height": 2240,
    "width": 3545,
    "x": -3226,
    "y": -1315
  },
  "groupLayout": {
    "_class": "MSImmutableFreeformGroupLayout"
  },
  "hasBackgroundColor": true,
  "hasClickThrough": false,
  "hasClippingMask": false,
  "horizontalRulerData": {
    "_class": "rulerData",
    "base": 0,
    "guides": [
    ]
  },
  "includeBackgroundColorInExport": true,
  "includeInCloudUpload": true,
  "isFixedToViewport": false,
  "isFlippedHorizontal": false,
  "isFlippedVertical": false,
  "isFlowHome": false,
  "isLocked": false,
  "isVisible": true,
  "layerListExpandedType": 1,
  "layers": [
    {
      "class": "group",
      "id": "E0292395-B26A-4A3A-9AE3-D43CEB61C42A"
    },
    {
      "class": "group",
      "id": "AF7F354E-E291-4BA1-B347-4777451CA400"
    },
    {
      "class": "group",
      "id": "D91FB256-5CCB-465D-A1AA-0448B5547BAE"
    },
    {
      "class": "group",
      "id": "4A6D3CB5-FC1F-4ACB-9A1B-C9CA07BF13FE"
    },
    {
      "class": "shapePath",
      "id": "40B3066F-8611-4973-8920-9079F1B56121"
    },
    {
      "class": "shapePath",
      "id": "80673E02-A974-4F19-8AC8-1E3CE865D11A"
    },
    {
      "class": "shapePath",
      "id": "372A4F75-EE19-49A6-8804-AEFE8B546F42"
    },
    {
      "class": "shapePath",
      "id": "91DD9D7C-C2F0-4411-92F0-3A9B13E7C5C6"
    },
    {
      "class": "group",
      "id": "0AA42D57-C1C9-4ED7-9573-5169A20F33BB"
    }
  ],
  "name": "First GPSBud Wireframes",
  "nameIsFixed": true,
  "presetDictionary": {
  },
  "resizesContent": false,
  "resizingConstraint": 63,
  "resizingType": 0,
  "rotation": 0,
  "shouldBreakMaskChain": true,
  "style": {
    "_class": "style",
    "blur": {
      "_class": "blur",
      "center": "{0.5, 0.5}",
      "isEnabled": false,
      "motionAngle": 0,
      "radius": 10,
      "saturation": 1,
      "type": 0
    },
    "borderOptions": {
      "_class": "borderOptions",
      "dashPattern": [
      ],
      "isEnabled": true,
      "lineCapStyle": 0,
      "lineJoinStyle": 0
    },
    "borders": [
    ],
    "colorControls": {
      "_class": "colorControls",
      "brightness": 0,
      "contrast": 1,
      "hue": 0,
      "isEnabled": false,
      "saturation": 1
    },
    "contextSettings": {
      "_class": "graphicsContextSettings",
      "blendMode": 0,
      "opacity": 1
    },
    "do_objectID": "CFE2AB83-D885-4051-AB2E-636CCFEB34CD",
    "endMarkerType": 0,
    "fills": [
    ],
    "innerShadows": [
    ],
    "miterLimit": 10,
    "shadows": [
    ],
    "startMarkerType": 0,
    "windingRule": 1
  },
  "verticalRulerData": {
    "_class": "rulerData",
    "base": 0,
    "guides": [
    ]
  }
}