{
  "_class": "group",
  "booleanOperation": -1,
  "clippingMaskMode": 0,
  "do_objectID": "F2069713-F4B7-4421-983C-E5F8FAB53E8B",
  "exportOptions": {
    "_class": "exportOptions",
    "exportFormats": [
    ],
    "includedLayerIds": [
    ],
    "layerOptions": 0,
    "shouldTrim": false
  },
  "frame": {
    "_class": "rect",
    "constrainProportions": false,
    "height": 18,
    "width": 25,
    "x": 79,
    "y": 13
  },
  "groupLayout": {
    "_class": "MSImmutableFreeformGroupLayout"
  },
  "hasClickThrough": false,
  "hasClippingMask": false,
  "isFixedToViewport": false,
  "isFlippedHorizontal": false,
  "isFlippedVertical": false,
  "isLocked": false,
  "isVisible": true,
  "layerListExpandedType": 2,
  "layers": [
    {
      "class": "shapePath",
      "id": "79BD9C36-0444-41E5-B6AD-96E60271CD73"
    },
    {
      "class": "shapePath",
      "id": "A1EFA49A-1BC7-4A70-A699-4ED9A612CFCF"
    },
    {
      "class": "shapePath",
      "id": "BC90DD4E-C5EF-4A54-BE96-2DC521897774"
    },
    {
      "class": "oval",
      "id": "F4E81706-886A-44F3-B790-4876661B9E92"
    },
    {
      "class": "oval",
      "id": "6D5A3D20-D0B8-4F91-AF12-70538EF1CED0"
    },
    {
      "class": "oval",
      "id": "B287C197-AAF0-43A1-85E8-68B34CB075B4"
    }
  ],
  "name": "filter",
  "nameIsFixed": false,
  "resizingConstraint": 63,
  "resizingType": 0,
  "rotation": 0,
  "shouldBreakMaskChain": false,
  "style": {
    "_class": "style",
    "blur": {
      "_class": "blur",
      "center": "{0.5, 0.5}",
      "isEnabled": false,
      "motionAngle": 0,
      "radius": 12.5,
      "saturation": 1,
      "type": 0
    },
    "borderOptions": {
      "_class": "borderOptions",
      "dashPattern": [
      ],
      "isEnabled": true,
      "lineCapStyle": 0,
      "lineJoinStyle": 0
    },
    "borders": [
    ],
    "colorControls": {
      "_class": "colorControls",
      "brightness": 0,
      "contrast": 1,
      "hue": 0,
      "isEnabled": false,
      "saturation": 1
    },
    "contextSettings": {
      "_class": "graphicsContextSettings",
      "blendMode": 0,
      "opacity": 1
    },
    "do_objectID": "E16AF2E5-EC28-4023-9369-8AD9C46A03D9",
    "endMarkerType": 0,
    "fills": [
    ],
    "innerShadows": [
    ],
    "miterLimit": 10,
    "shadows": [
    ],
    "startMarkerType": 0,
    "windingRule": 1
  }
}